scheduler/__init__.py
scheduler/helpers.py
sop_scheduler-0.0.1.dist-info/METADATA
sop_scheduler-0.0.1.dist-info/WHEEL
sop_scheduler-0.0.1.dist-info/top_level.txt
sop_scheduler-0.0.1.dist-info/RECORD
