Metadata-Version: 2.1
Name: sop-scheduler
Version: 0.0.1
Summary: SoPIoT Scheduler
Home-page: https://iris.snu.ac.kr
Author: caplab
Author-email: caplab94@gmail.com
License: MIT
Requires-Python: >=3
